{
    "variables": {
        "ssh_name": "vagrant",
        "ssh_pass": "vagrant"
    },
    "builders": [{
        "type": "virtualbox-iso",
        "virtualbox_version_file": ".vbox_version",
        "headless": false,

        "guest_os_type": "RedHat_64",
        "disk_size": 20480,
        "hard_drive_interface": "sata",

        "iso_url": "http://mirror.linux.lg.ua/centos/7.0.1406/isos/x86_64/CentOS-7.0-1406-x86_64-NetInstall.iso",
        "iso_checksum": "df6dfdd25ebf443ca3375188d0b4b7f92f4153dc910b17bccc886bd54a7b7c86",
        "iso_checksum_type": "sha256",

        "boot_command": [
            "<tab> text ks=http://{{ .HTTPIP }}:{{ .HTTPPort }}/centos7/anaconda-ks.cfg<enter><wait>"
        ],
        "boot_wait": "12s",

        "http_directory": "http",
        "guest_additions_path": "VBoxGuestAdditions_{{.Version}}.iso",

        "ssh_username": "{{user `ssh_name`}}",
        "ssh_password": "{{user `ssh_pass`}}",
        "ssh_port": 22,
        "ssh_wait_timeout": "10000s",

        "vboxmanage": [
            ["modifyvm", "{{.Name}}", "--memory", "512"],
            ["modifyvm", "{{.Name}}", "--cpus", "2"]
        ],

        "shutdown_command": "echo '{{user `ssh_name`}}'|sudo -S /sbin/halt -h -p"
    }],
    "post-processors": [{
        "output": "build/CentOS-7.box",
        "type": "vagrant"
    }],
    "provisioners": [{
        "type": "shell",
        "execute_command": "echo 'vagrant' | {{.Vars}} sudo -S -E bash '{{.Path}}'",
        "scripts": [
            "scripts/centos7/vboxguest.sh",
            "scripts/centos7/vagrant.sh",
            "scripts/centos7/compact.sh"
        ]
    }]
}